sylk_docs.py
sylk_docs-0.0.3.dist-info/METADATA
sylk_docs-0.0.3.dist-info/WHEEL
sylk_docs-0.0.3.dist-info/entry_points.txt
sylk_docs-0.0.3.dist-info/top_level.txt
sylk_docs-0.0.3.dist-info/RECORD
