Metadata-Version: 2.1
Name: sylk-docs
Version: 0.0.3
Summary: A sylk CLI plugin for interacting with docusaurus-sylk plugin for Docusaurus
Home-page: https://sylk.build/
Author-email: Sylk Team <contact@sylk.build>
Classifier: Programming Language :: Python :: 3.7
Classifier: Programming Language :: Python :: 3.8
Classifier: Programming Language :: Python :: 3.9
Requires-Python: ~=3.7
Requires-Dist: sylk
